appbase/Application.py
appbase/Launcher.py
appbase/MainWindow.py
appbase/MultiWorkspaceWindow.py
appbase/Server.py
appbase/Session.py
appbase/__init__.py
appbase/dialogs/FirstStart.py
appbase/dialogs/__init__.py
appbase/mainWindowRessources/__init__.py
appbase/mainWindowRessources/menuShortcuts.py
appbase/mainWindowRessources/menuabout.py
appbase/mainWindowRessources/menubar.py
appbase/mainWindowRessources/menupreferences.py
appbase/media/launcher_logo.svg
appbase/media/icons/__init__.py
appbase/media/icons/approve.svg
appbase/media/icons/bug.png
appbase/media/icons/delete.svg
appbase/media/icons/findReplace.svg
appbase/media/icons/new.svg
appbase/media/icons/rename.svg
appbase-0.3.4.dist-info/DESCRIPTION.rst
appbase-0.3.4.dist-info/METADATA
appbase-0.3.4.dist-info/RECORD
appbase-0.3.4.dist-info/WHEEL
appbase-0.3.4.dist-info/metadata.json
appbase-0.3.4.dist-info/top_level.txt
