Metadata-Version: 2.0
Name: appbase
Version: 0.3.4
Summary: 
Requires-Dist: fancytools (>=0.2)
Requires-Dist: fancywidgets (>=0.1)
Requires-Dist: numpy (>=1.7.1)
